causaliq_core/__init__.py
causaliq_core/cli.py
causaliq_core/py.typed
causaliq_core/bn/__init__.py
causaliq_core/bn/bn.py
causaliq_core/bn/bnfit.py
causaliq_core/bn/dist/__init__.py
causaliq_core/bn/dist/cnd.py
causaliq_core/bn/dist/cpt.py
causaliq_core/bn/dist/lingauss.py
causaliq_core/bn/io/__init__.py
causaliq_core/bn/io/common.py
causaliq_core/bn/io/dsc.py
causaliq_core/bn/io/xdsl.py
causaliq_core/graph/__init__.py
causaliq_core/graph/convert.py
causaliq_core/graph/dag.py
causaliq_core/graph/enums.py
causaliq_core/graph/pdag.py
causaliq_core/graph/sdg.py
causaliq_core/graph/io/__init__.py
causaliq_core/graph/io/bayesys.py
causaliq_core/graph/io/common.py
causaliq_core/graph/io/tetrad.py
causaliq_core/utils/__init__.py
causaliq_core/utils/environment.py
causaliq_core/utils/io.py
causaliq_core/utils/math.py
causaliq_core/utils/random.py
causaliq_core/utils/same.py
causaliq_core/utils/timing.py
causaliq_core-0.3.0.dist-info/licenses/LICENSE
causaliq_core-0.3.0.dist-info/METADATA
causaliq_core-0.3.0.dist-info/WHEEL
causaliq_core-0.3.0.dist-info/entry_points.txt
causaliq_core-0.3.0.dist-info/top_level.txt
causaliq_core-0.3.0.dist-info/RECORD
