Metadata-Version: 2.4
Name: causaliq-core
Version: 0.3.0
Summary: Core utilities and classes for the CausalIQ ecosystem
Author-email: CausalIQ <info@causaliq.org>
Maintainer-email: "Dr. Ken Kitson" <info@causaliq.org>
License: MIT
Project-URL: Homepage, https://github.com/causaliq/causaliq-core
Project-URL: Documentation, https://github.com/causaliq/causaliq-core#readme
Project-URL: Repository, https://github.com/causaliq/causaliq-core
Project-URL: Bug Tracker, https://github.com/causaliq/causaliq-core/issues
Keywords: causaliq
Classifier: Development Status :: 2 - Pre-Alpha
Classifier: Intended Audience :: Science/Research
Classifier: License :: OSI Approved :: MIT License
Classifier: Operating System :: OS Independent
Classifier: Programming Language :: Python :: 3
Classifier: Programming Language :: Python :: 3.9
Classifier: Programming Language :: Python :: 3.10
Classifier: Programming Language :: Python :: 3.11
Classifier: Programming Language :: Python :: 3.12
Classifier: Topic :: Scientific/Engineering
Classifier: Topic :: Software Development :: Libraries :: Python Modules
Requires-Python: >=3.9
License-File: LICENSE
Requires-Dist: click>=8.0.0
Requires-Dist: numpy>=1.20.0
Requires-Dist: pandas>=1.3.0
Requires-Dist: platformdirs>=3.0.0
Requires-Dist: py-cpuinfo>=9.0.0
Requires-Dist: psutil>=5.8.0
Requires-Dist: scikit-learn>=1.0.0
Provides-Extra: dev
Requires-Dist: pytest>=7.0.0; extra == "dev"
Requires-Dist: pytest-cov>=4.0.0; extra == "dev"
Requires-Dist: pytest-mock>=3.10.0; extra == "dev"
Requires-Dist: black>=22.0.0; extra == "dev"
Requires-Dist: isort>=5.10.0; extra == "dev"
Requires-Dist: flake8>=5.0.0; extra == "dev"
Requires-Dist: mypy>=1.0.0; extra == "dev"
Requires-Dist: types-requests>=2.32.0; extra == "dev"
Requires-Dist: types-psutil>=5.9.0; extra == "dev"
Requires-Dist: pandas-stubs>=1.5.0; extra == "dev"
Requires-Dist: pre-commit>=2.20.0; extra == "dev"
Requires-Dist: build>=0.8.0; extra == "dev"
Requires-Dist: twine>=4.0.0; extra == "dev"
Provides-Extra: test
Requires-Dist: pytest>=7.0.0; extra == "test"
Requires-Dist: pytest-cov>=4.0.0; extra == "test"
Requires-Dist: pytest-mock>=3.10.0; extra == "test"
Provides-Extra: docs
Requires-Dist: mkdocs>=1.5.0; extra == "docs"
Requires-Dist: mkdocs-material>=9.0.0; extra == "docs"
Requires-Dist: mkdocstrings==0.30.1; extra == "docs"
Requires-Dist: mkdocstrings-python==1.18.2; extra == "docs"
Dynamic: license-file
